README.md
setup.py
coff/__init__.py
coff.egg-info/PKG-INFO
coff.egg-info/SOURCES.txt
coff.egg-info/dependency_links.txt
coff.egg-info/top_level.txt
coff.egg-info/zip-safe