Metadata-Version: 1.1
Name: coff
Version: 0.0.2
Summary: common object file format parser
Home-page: http://github.com/jeppeter/py-coff
Author: jeppeter Wang
Author-email: jeppeter@gmail.com
License: MIT
Platform: UNKNOWN
Classifier: Programming Language :: Python
Classifier: License :: OSI Approved :: MIT License
Classifier: Operating System :: OS Independent
